{"cameraMode":{"drawMode":0,"name":"Shaded","section":"Shading Mode"},"sceneLighting":true,"audioPlay":false,"sceneViewState":{"m_AlwaysRefresh":false,"showFog":true,"showSkybox":true,"showFlares":true,"showImageEffects":true,"showParticleSystems":true,"showVisualEffectGraphs":true,"m_FxEnabled":true},"in2DMode":false,"pivot":{"x":46.20610809326172,"y":13.577871322631836,"z":294.3058166503906},"rotation":{"x":0.18134774267673493,"y":0.3304745554924011,"z":-0.06486372649669647,"w":0.9239548444747925},"size":33.695152282714847,"orthographic":false}